{
  "_description": "Centralized label mappings for Earth Engine land cover datasets",
  "_updated": "2026-04-19",
  "_comment": "This file contains label mappings, class names, and visualization palettes for various land cover datasets. Palettes harmonized so that recurring concepts (Trees, Grassland, Cropland, Built-up, Water, etc.) share the same canonical color across datasets. Anchored on the ESA WorldCover (UN/FAO LCCS) color scheme, extended with Dynamic World colors for classes WorldCover does not define.",
  "dynamicworld": {
    "name": "Google Dynamic World",
    "description": "Near real-time 10m land use/land cover dataset",
    "source": "Google/World Resources Institute",
    "resolution": 10,
    "num_classes": 9,
    "label_mapping": {
      "0": 0,
      "1": 1,
      "2": 2,
      "3": 3,
      "4": 4,
      "5": 5,
      "6": 6,
      "7": 7,
      "8": 8
    },
    "labels": [
      0,
      1,
      2,
      3,
      4,
      5,
      6,
      7,
      8
    ],
    "class_names": [
      "Water",
      "Trees",
      "Grass",
      "Flooded Vegetation",
      "Crops",
      "Shrub and Scrub",
      "Built Area",
      "Bare Ground",
      "Snow and Ice"
    ],
    "palette": [
      "#0064C8",
      "#006400",
      "#FFFF4C",
      "#7A87C6",
      "#F096FF",
      "#FFBB22",
      "#FA0000",
      "#B4B4B4",
      "#F0F0F0"
    ],
    "vis_params": {
      "min": 0,
      "max": 8
    }
  },
  "worldcover": {
    "name": "ESA WorldCover",
    "description": "ESA WorldCover 10m land cover dataset",
    "source": "European Space Agency",
    "year": 2020,
    "resolution": 10,
    "num_classes": 12,
    "label_mapping": {
      "10": 0,
      "20": 1,
      "30": 2,
      "40": 3,
      "50": 4,
      "60": 5,
      "70": 6,
      "80": 7,
      "90": 8,
      "95": 9,
      "100": 10,
      "0": 11
    },
    "original_values": [
      10,
      20,
      30,
      40,
      50,
      60,
      70,
      80,
      90,
      95,
      100,
      0
    ],
    "labels": [
      0,
      1,
      2,
      3,
      4,
      5,
      6,
      7,
      8,
      9,
      10,
      11
    ],
    "class_names": [
      "Tree cover",
      "Shrubland",
      "Grassland",
      "Cropland",
      "Built-up",
      "Bare/Sparse vegetation",
      "Snow and Ice",
      "Permanent Water Bodies",
      "Herbaceous Wetland",
      "Mangroves",
      "Moss and Lichen",
      "No Data"
    ],
    "palette": [
      "#006400",
      "#FFBB22",
      "#FFFF4C",
      "#F096FF",
      "#FA0000",
      "#B4B4B4",
      "#F0F0F0",
      "#0064C8",
      "#0096A0",
      "#00CF75",
      "#FAE6A0",
      "#000000"
    ],
    "vis_params": {
      "min": 10,
      "max": 100
    }
  },
  "glad_glclu": {
    "name": "GLAD Global Land Cover and Land Use",
    "description": "GLAD GLCLU 30m land cover/land use dataset (2000-2020) with detailed vegetation height classes",
    "source": "University of Maryland GLAD",
    "resolution": 30,
    "years_available": "2000-2020",
    "num_classes": 113,
    "label_mapping": {
      "0": 0,
      "1": 1,
      "2": 2,
      "3": 3,
      "4": 4,
      "5": 5,
      "6": 6,
      "7": 7,
      "8": 8,
      "9": 9,
      "10": 10,
      "11": 11,
      "12": 12,
      "13": 13,
      "14": 14,
      "15": 15,
      "16": 16,
      "17": 17,
      "18": 18,
      "19": 19,
      "20": 20,
      "21": 21,
      "22": 22,
      "23": 23,
      "24": 24,
      "25": 25,
      "26": 26,
      "27": 27,
      "28": 28,
      "29": 29,
      "30": 30,
      "31": 31,
      "32": 32,
      "33": 33,
      "34": 34,
      "35": 35,
      "36": 36,
      "37": 37,
      "38": 38,
      "39": 39,
      "40": 40,
      "41": 41,
      "42": 42,
      "43": 43,
      "44": 44,
      "45": 45,
      "46": 46,
      "47": 47,
      "48": 48,
      "100": 50,
      "101": 51,
      "102": 52,
      "103": 53,
      "104": 54,
      "105": 55,
      "106": 56,
      "107": 57,
      "108": 58,
      "109": 59,
      "110": 60,
      "111": 61,
      "112": 62,
      "113": 63,
      "114": 64,
      "115": 65,
      "116": 66,
      "117": 67,
      "118": 68,
      "119": 69,
      "120": 70,
      "121": 71,
      "122": 72,
      "123": 73,
      "124": 74,
      "125": 75,
      "126": 76,
      "127": 77,
      "128": 78,
      "129": 79,
      "130": 80,
      "131": 81,
      "132": 82,
      "133": 83,
      "134": 84,
      "135": 85,
      "136": 86,
      "137": 87,
      "138": 88,
      "139": 89,
      "140": 90,
      "141": 91,
      "142": 92,
      "143": 93,
      "144": 94,
      "145": 95,
      "146": 96,
      "147": 97,
      "148": 98,
      "200": 100,
      "201": 101,
      "202": 102,
      "203": 103,
      "204": 104,
      "205": 105,
      "206": 106,
      "207": 107,
      "241": 108,
      "244": 109,
      "250": 110,
      "254": 111
    },
    "original_values": [
      0,
      1,
      2,
      3,
      4,
      5,
      6,
      7,
      8,
      9,
      10,
      11,
      12,
      13,
      14,
      15,
      16,
      17,
      18,
      19,
      20,
      21,
      22,
      23,
      24,
      25,
      26,
      27,
      28,
      29,
      30,
      31,
      32,
      33,
      34,
      35,
      36,
      37,
      38,
      39,
      40,
      41,
      42,
      43,
      44,
      45,
      46,
      47,
      48,
      100,
      101,
      102,
      103,
      104,
      105,
      106,
      107,
      108,
      109,
      110,
      111,
      112,
      113,
      114,
      115,
      116,
      117,
      118,
      119,
      120,
      121,
      122,
      123,
      124,
      125,
      126,
      127,
      128,
      129,
      130,
      131,
      132,
      133,
      134,
      135,
      136,
      137,
      138,
      139,
      140,
      141,
      142,
      143,
      144,
      145,
      146,
      147,
      148,
      200,
      201,
      202,
      203,
      204,
      205,
      206,
      207,
      241,
      244,
      250,
      254
    ],
    "labels": [
      0,
      1,
      2,
      3,
      4,
      5,
      6,
      7,
      8,
      9,
      10,
      11,
      12,
      13,
      14,
      15,
      16,
      17,
      18,
      19,
      20,
      21,
      22,
      23,
      24,
      25,
      26,
      27,
      28,
      29,
      30,
      31,
      32,
      33,
      34,
      35,
      36,
      37,
      38,
      39,
      40,
      41,
      42,
      43,
      44,
      45,
      46,
      47,
      48,
      50,
      51,
      52,
      53,
      54,
      55,
      56,
      57,
      58,
      59,
      60,
      61,
      62,
      63,
      64,
      65,
      66,
      67,
      68,
      69,
      70,
      71,
      72,
      73,
      74,
      75,
      76,
      77,
      78,
      79,
      80,
      81,
      82,
      83,
      84,
      85,
      86,
      87,
      88,
      89,
      90,
      91,
      92,
      93,
      94,
      95,
      96,
      97,
      98,
      100,
      101,
      102,
      103,
      104,
      105,
      106,
      107,
      108,
      109,
      110,
      111
    ],
    "class_names": [
      "Terra Firma: True desert (3% short vegetation)",
      "Terra Firma: 7% short vegetation",
      "Terra Firma: Semi-arid (11% short vegetation)",
      "Terra Firma: 15% short vegetation",
      "Terra Firma: 19% short vegetation",
      "Terra Firma: 23% short vegetation",
      "Terra Firma: 27% short vegetation",
      "Terra Firma: 31% short vegetation",
      "Terra Firma: 35% short vegetation",
      "Terra Firma: 39% short vegetation",
      "Terra Firma: 43% short vegetation",
      "Terra Firma: 47% short vegetation",
      "Terra Firma: 51% short vegetation",
      "Terra Firma: 55% short vegetation",
      "Terra Firma: 59% short vegetation",
      "Terra Firma: 63% short vegetation",
      "Terra Firma: 67% short vegetation",
      "Terra Firma: 71% short vegetation",
      "Terra Firma: 75% short vegetation",
      "Terra Firma: Dense short vegetation (79%)",
      "Terra Firma: Dense short vegetation (83%)",
      "Terra Firma: Dense short vegetation (87%)",
      "Terra Firma: Dense short vegetation (91%)",
      "Terra Firma: Dense short vegetation (95%)",
      "Terra Firma: Dense short vegetation (100%)",
      "Terra Firma: Tree cover (3m trees)",
      "Terra Firma: Tree cover (4m trees)",
      "Terra Firma: Tree cover (5m trees)",
      "Terra Firma: Tree cover (6m trees)",
      "Terra Firma: Tree cover (7m trees)",
      "Terra Firma: Tree cover (8m trees)",
      "Terra Firma: Tree cover (9m trees)",
      "Terra Firma: Tree cover (10m trees)",
      "Terra Firma: Tree cover (11m trees)",
      "Terra Firma: Tree cover (12m trees)",
      "Terra Firma: Tree cover (13m trees)",
      "Terra Firma: Tree cover (14m trees)",
      "Terra Firma: Tree cover (15m trees)",
      "Terra Firma: Tree cover (16m trees)",
      "Terra Firma: Tree cover (17m trees)",
      "Terra Firma: Tree cover (18m trees)",
      "Terra Firma: Tree cover (19m trees)",
      "Terra Firma: Tree cover (20m trees)",
      "Terra Firma: Tree cover (21m trees)",
      "Terra Firma: Tree cover (22m trees)",
      "Terra Firma: Tree cover (23m trees)",
      "Terra Firma: Tree cover (24m trees)",
      "Terra Firma: Tree cover (25m trees)",
      "Terra Firma: Tree cover (>25m trees)",
      "Wetland: Salt pan (3% short vegetation)",
      "Wetland: 7% short vegetation",
      "Wetland: Sparse vegetation (11%)",
      "Wetland: 15% short vegetation",
      "Wetland: 19% short vegetation",
      "Wetland: 23% short vegetation",
      "Wetland: 27% short vegetation",
      "Wetland: 31% short vegetation",
      "Wetland: 35% short vegetation",
      "Wetland: 39% short vegetation",
      "Wetland: 43% short vegetation",
      "Wetland: 47% short vegetation",
      "Wetland: 51% short vegetation",
      "Wetland: 55% short vegetation",
      "Wetland: 59% short vegetation",
      "Wetland: 63% short vegetation",
      "Wetland: 67% short vegetation",
      "Wetland: 71% short vegetation",
      "Wetland: 75% short vegetation",
      "Wetland: Dense short vegetation (79%)",
      "Wetland: Dense short vegetation (83%)",
      "Wetland: Dense short vegetation (87%)",
      "Wetland: Dense short vegetation (91%)",
      "Wetland: Dense short vegetation (95%)",
      "Wetland: Dense short vegetation (100%)",
      "Wetland: Tree cover (3m trees)",
      "Wetland: Tree cover (4m trees)",
      "Wetland: Tree cover (5m trees)",
      "Wetland: Tree cover (6m trees)",
      "Wetland: Tree cover (7m trees)",
      "Wetland: Tree cover (8m trees)",
      "Wetland: Tree cover (9m trees)",
      "Wetland: Tree cover (10m trees)",
      "Wetland: Tree cover (11m trees)",
      "Wetland: Tree cover (12m trees)",
      "Wetland: Tree cover (13m trees)",
      "Wetland: Tree cover (14m trees)",
      "Wetland: Tree cover (15m trees)",
      "Wetland: Tree cover (16m trees)",
      "Wetland: Tree cover (17m trees)",
      "Wetland: Tree cover (18m trees)",
      "Wetland: Tree cover (19m trees)",
      "Wetland: Tree cover (20m trees)",
      "Wetland: Tree cover (21m trees)",
      "Wetland: Tree cover (22m trees)",
      "Wetland: Tree cover (23m trees)",
      "Wetland: Tree cover (24m trees)",
      "Wetland: Tree cover (25m trees)",
      "Wetland: Tree cover (>25m trees)",
      "Open surface water: 20-29% of year",
      "Open surface water: 30-39% of year",
      "Open surface water: 40-49% of year",
      "Open surface water: 50-59% of year",
      "Open surface water: 60-69% of year",
      "Open surface water: 70-79% of year",
      "Open surface water: 80-89% of year",
      "Open surface water: 90-100% of year",
      "Snow/Ice",
      "Cropland",
      "Built-up",
      "Ocean"
    ],
    "palette": [
      "#F5E6B8",
      "#F5E7B4",
      "#F6E8AF",
      "#F6E9AA",
      "#F7EAA6",
      "#F7EBA2",
      "#F8EC9D",
      "#F8ED98",
      "#F8EE94",
      "#F9EF90",
      "#F9F08B",
      "#FAF186",
      "#FAF282",
      "#FAF47E",
      "#FBF579",
      "#FBF674",
      "#FCF770",
      "#FCF86C",
      "#FCF967",
      "#FDFA62",
      "#FDFB5E",
      "#FEFC5A",
      "#FEFD55",
      "#FFFE50",
      "#FFFF4C",
      "#A6C9A6",
      "#97C097",
      "#89B789",
      "#7BAE7B",
      "#6CA66C",
      "#5E9D5E",
      "#4F944F",
      "#418B41",
      "#328332",
      "#247A24",
      "#167116",
      "#076807",
      "#006200",
      "#005D00",
      "#005800",
      "#005300",
      "#004E00",
      "#004A00",
      "#004500",
      "#004000",
      "#003B00",
      "#003700",
      "#003200",
      "#002D00",
      "#B2E0E2",
      "#A4D9DD",
      "#95D3D7",
      "#86CDD2",
      "#77C7CC",
      "#68C1C7",
      "#59BBC1",
      "#4AB5BC",
      "#3CAEB6",
      "#2DA8B1",
      "#1EA2AB",
      "#0F9CA6",
      "#0096A0",
      "#009099",
      "#008A93",
      "#00838C",
      "#007D85",
      "#00777F",
      "#007078",
      "#006A71",
      "#00646B",
      "#005E64",
      "#00585D",
      "#005157",
      "#004B50",
      "#00CF75",
      "#00CA70",
      "#00C66B",
      "#00C166",
      "#00BC61",
      "#00B85C",
      "#00B356",
      "#00AE51",
      "#00AA4C",
      "#00A547",
      "#00A042",
      "#009C3D",
      "#009738",
      "#009333",
      "#008E2E",
      "#008929",
      "#008524",
      "#00801F",
      "#007B19",
      "#007714",
      "#00720F",
      "#006D0A",
      "#006905",
      "#006400",
      "#99C1E9",
      "#6DA6E0",
      "#428CD6",
      "#1671CD",
      "#005EBD",
      "#0053A6",
      "#00478F",
      "#003C78",
      "#F0F0F0",
      "#F096FF",
      "#FA0000",
      "#003E80"
    ],
    "general_classes": {
      "Terra Firma": {
        "range": [
          0,
          48
        ],
        "description": "Terrestrial areas with varying vegetation cover and tree heights"
      },
      "Wetland": {
        "range": [
          100,
          148
        ],
        "description": "Wetland areas with varying vegetation cover and tree heights"
      },
      "Open surface water": {
        "range": [
          200,
          207
        ],
        "description": "Water present 20-100% of year"
      },
      "Snow/Ice": {
        "value": 241
      },
      "Cropland": {
        "value": 244
      },
      "Built-up": {
        "value": 250
      },
      "Ocean": {
        "value": 254
      }
    },
    "simplified_groups": {
      "num_groups": 11,
      "group_mapping": {
        "0": 0,
        "1": 0,
        "2": 1,
        "3": 1,
        "4": 1,
        "5": 1,
        "6": 1,
        "7": 1,
        "8": 1,
        "9": 1,
        "10": 1,
        "11": 1,
        "12": 1,
        "13": 1,
        "14": 1,
        "15": 1,
        "16": 1,
        "17": 1,
        "18": 1,
        "19": 2,
        "20": 2,
        "21": 2,
        "22": 2,
        "23": 2,
        "24": 2,
        "25": 3,
        "26": 3,
        "27": 3,
        "28": 3,
        "29": 3,
        "30": 3,
        "31": 3,
        "32": 3,
        "33": 3,
        "34": 3,
        "35": 3,
        "36": 3,
        "37": 3,
        "38": 3,
        "39": 3,
        "40": 3,
        "41": 3,
        "42": 3,
        "43": 3,
        "44": 3,
        "45": 3,
        "46": 3,
        "47": 3,
        "48": 3,
        "100": 4,
        "101": 4,
        "102": 4,
        "103": 4,
        "104": 4,
        "105": 4,
        "106": 4,
        "107": 4,
        "108": 4,
        "109": 4,
        "110": 4,
        "111": 4,
        "112": 4,
        "113": 4,
        "114": 4,
        "115": 4,
        "116": 4,
        "117": 4,
        "118": 4,
        "119": 4,
        "120": 4,
        "121": 4,
        "122": 4,
        "123": 4,
        "124": 4,
        "125": 5,
        "126": 5,
        "127": 5,
        "128": 5,
        "129": 5,
        "130": 5,
        "131": 5,
        "132": 5,
        "133": 5,
        "134": 5,
        "135": 5,
        "136": 5,
        "137": 5,
        "138": 5,
        "139": 5,
        "140": 5,
        "141": 5,
        "142": 5,
        "143": 5,
        "144": 5,
        "145": 5,
        "146": 5,
        "147": 5,
        "148": 5,
        "200": 6,
        "201": 6,
        "202": 6,
        "203": 6,
        "204": 6,
        "205": 6,
        "206": 6,
        "207": 6,
        "241": 7,
        "244": 8,
        "250": 9,
        "254": 10
      },
      "group_labels": [
        0,
        1,
        2,
        3,
        4,
        5,
        6,
        7,
        8,
        9,
        10
      ],
      "group_names": [
        "True Desert",
        "Semi-arid",
        "Dense Short Vegetation",
        "Tree Cover",
        "Wetland Vegetation",
        "Wetland Trees",
        "Water",
        "Snow and Ice",
        "Cropland",
        "Built-up",
        "Ocean"
      ],
      "group_colors": [
        "#F5E6B8",
        "#FAF282",
        "#FFFF4C",
        "#006400",
        "#0096A0",
        "#00CF75",
        "#0064C8",
        "#F0F0F0",
        "#F096FF",
        "#FA0000",
        "#003E80"
      ],
      "group_ranges": {
        "True Desert": [
          0,
          1
        ],
        "Semi-arid": [
          2,
          18
        ],
        "Dense Short Vegetation": [
          19,
          24
        ],
        "Tree Cover": [
          25,
          48
        ],
        "Wetland Vegetation": [
          100,
          124
        ],
        "Wetland Trees": [
          125,
          148
        ],
        "Water": [
          200,
          207
        ],
        "Snow and Ice": [
          241
        ],
        "Cropland": [
          244
        ],
        "Built-up": [
          250
        ],
        "Ocean": [
          254
        ]
      }
    },
    "vis_params": {
      "min": 0,
      "max": 254
    },
    "note": "GLAD GLCLU provides detailed vegetation height (3m-25m+) and cover density (3%-100%) classifications for both terrestrial and wetland areas. Values 49-99 and 149-199 are not used."
  },
  "esri_lulc": {
    "name": "Sentinel-2 10m Land Use/Land Cover",
    "description": "ESA Sentinel-2 derived land use/land cover (Impact Observatory)",
    "source": "Impact Observatory/ESA",
    "resolution": 10,
    "years_available": "2017-present",
    "num_classes": 9,
    "label_mapping": {
      "1": 0,
      "2": 1,
      "4": 2,
      "5": 3,
      "7": 4,
      "8": 5,
      "9": 6,
      "10": 7,
      "11": 8
    },
    "original_values": [
      1,
      2,
      4,
      5,
      7,
      8,
      9,
      10,
      11
    ],
    "labels": [
      0,
      1,
      2,
      3,
      4,
      5,
      6,
      7,
      8
    ],
    "class_names": [
      "Water",
      "Trees",
      "Flooded Vegetation",
      "Crops",
      "Built Area",
      "Bare Ground",
      "Snow/Ice",
      "Clouds",
      "Rangeland"
    ],
    "palette": [
      "#0064C8",
      "#006400",
      "#7A87C6",
      "#F096FF",
      "#FA0000",
      "#B4B4B4",
      "#F0F0F0",
      "#FFFFFF",
      "#FFFF4C"
    ],
    "vis_params": {
      "min": 0,
      "max": 8
    }
  },
  "glc_fcs30d": {
    "name": "GLC_FCS30D Global Land Cover",
    "description": "GLC_FCS30D Global 30-meter Land Cover Change Dataset (1985-2022)",
    "source": "Tsinghua University",
    "resolution": 30,
    "years_available": "1985-2022",
    "num_classes": 36,
    "label_mapping": {
      "10": 0,
      "11": 1,
      "12": 2,
      "20": 3,
      "51": 4,
      "52": 5,
      "61": 6,
      "62": 7,
      "71": 8,
      "72": 9,
      "81": 10,
      "82": 11,
      "91": 12,
      "92": 13,
      "120": 14,
      "121": 15,
      "122": 16,
      "130": 17,
      "140": 18,
      "150": 19,
      "152": 20,
      "153": 21,
      "181": 22,
      "182": 23,
      "183": 24,
      "184": 25,
      "185": 26,
      "186": 27,
      "187": 28,
      "190": 29,
      "200": 30,
      "201": 31,
      "202": 32,
      "210": 33,
      "220": 34,
      "0": 35
    },
    "original_values": [
      10,
      11,
      12,
      20,
      51,
      52,
      61,
      62,
      71,
      72,
      81,
      82,
      91,
      92,
      120,
      121,
      122,
      130,
      140,
      150,
      152,
      153,
      181,
      182,
      183,
      184,
      185,
      186,
      187,
      190,
      200,
      201,
      202,
      210,
      220,
      0
    ],
    "labels": [
      0,
      1,
      2,
      3,
      4,
      5,
      6,
      7,
      8,
      9,
      10,
      11,
      12,
      13,
      14,
      15,
      16,
      17,
      18,
      19,
      20,
      21,
      22,
      23,
      24,
      25,
      26,
      27,
      28,
      29,
      30,
      31,
      32,
      33,
      34,
      35
    ],
    "class_names": [
      "Rainfed cropland",
      "Herbaceous cover cropland",
      "Tree or shrub cover (Orchard) cropland",
      "Irrigated cropland",
      "Open evergreen broadleaved forest",
      "Closed evergreen broadleaved forest",
      "Open deciduous broadleaved forest",
      "Closed deciduous broadleaved forest",
      "Open evergreen needle-leaved forest",
      "Closed evergreen needle-leaved forest",
      "Open deciduous needle-leaved forest",
      "Closed deciduous needle-leaved forest",
      "Open mixed leaf forest",
      "Closed mixed leaf forest",
      "Shrubland",
      "Evergreen shrubland",
      "Deciduous shrubland",
      "Grassland",
      "Lichens and mosses",
      "Sparse vegetation",
      "Sparse shrubland",
      "Sparse herbaceous",
      "Swamp",
      "Marsh",
      "Flooded flat",
      "Saline",
      "Mangrove",
      "Salt marsh",
      "Tidal flat",
      "Impervious surfaces",
      "Bare areas",
      "Consolidated bare areas",
      "Unconsolidated bare areas",
      "Water body",
      "Permanent ice and snow",
      "Filled value"
    ],
    "palette": [
      "#F8D0FF",
      "#F3A9FF",
      "#D484E1",
      "#9C62A6",
      "#B2D0B2",
      "#8BB88B",
      "#63A063",
      "#3C883C",
      "#147014",
      "#005E00",
      "#005200",
      "#004500",
      "#003900",
      "#002D00",
      "#FFDA85",
      "#FFBB22",
      "#A67A16",
      "#FFFF4C",
      "#FAE6A0",
      "#CECECE",
      "#B4B4B4",
      "#757575",
      "#8CD0D4",
      "#54B9BF",
      "#1CA2AA",
      "#008892",
      "#00CF75",
      "#006E75",
      "#005258",
      "#FA0000",
      "#CECECE",
      "#B4B4B4",
      "#757575",
      "#0064C8",
      "#F0F0F0",
      "#000000"
    ],
    "vis_params": {
      "min": 0,
      "max": 35
    },
    "simplified_groups": {
      "num_groups": 13,
      "group_mapping": {
        "10": 0,
        "11": 0,
        "12": 0,
        "20": 0,
        "51": 1,
        "52": 1,
        "61": 1,
        "62": 1,
        "71": 1,
        "72": 1,
        "81": 1,
        "82": 1,
        "91": 1,
        "92": 1,
        "120": 2,
        "121": 2,
        "122": 2,
        "130": 3,
        "140": 4,
        "150": 5,
        "152": 5,
        "153": 5,
        "181": 6,
        "182": 6,
        "183": 6,
        "184": 6,
        "185": 7,
        "186": 6,
        "187": 6,
        "190": 8,
        "200": 9,
        "201": 9,
        "202": 9,
        "210": 10,
        "220": 11,
        "0": 12
      },
      "group_labels": [
        0,
        1,
        2,
        3,
        4,
        5,
        6,
        7,
        8,
        9,
        10,
        11,
        12
      ],
      "group_names": [
        "Cropland",
        "Forest",
        "Shrubland",
        "Grassland",
        "Lichens and Mosses",
        "Sparse Vegetation",
        "Wetland",
        "Mangrove",
        "Impervious Surfaces",
        "Bare Areas",
        "Water",
        "Snow/Ice",
        "No Data"
      ],
      "group_colors": [
        "#F096FF",
        "#006400",
        "#FFBB22",
        "#FFFF4C",
        "#FAE6A0",
        "#B4B4B4",
        "#0096A0",
        "#00CF75",
        "#FA0000",
        "#B4B4B4",
        "#0064C8",
        "#F0F0F0",
        "#000000"
      ],
      "group_ranges": {
        "Cropland": [
          10,
          11,
          12,
          20
        ],
        "Forest": [
          51,
          52,
          61,
          62,
          71,
          72,
          81,
          82,
          91,
          92
        ],
        "Shrubland": [
          120,
          121,
          122
        ],
        "Grassland": [
          130
        ],
        "Lichens and Mosses": [
          140
        ],
        "Sparse Vegetation": [
          150,
          152,
          153
        ],
        "Wetland": [
          181,
          182,
          183,
          184,
          186,
          187
        ],
        "Mangrove": [
          185
        ],
        "Impervious Surfaces": [
          190
        ],
        "Bare Areas": [
          200,
          201,
          202
        ],
        "Water": [
          210
        ],
        "Snow/Ice": [
          220
        ],
        "No Data": [
          0
        ]
      }
    }
  },
  "sunstone_kenya_lulc_9C": {
    "name": "Sunstone Kenya Land Cover",
    "description": "sunstone_lulc_9classes Kenya 10-meter Land Cover Change Dataset (2017-2024)",
    "source": "Sunstone Institute",
    "resolution": 10,
    "years_available": "2017-2024",
    "num_classes": 10,
    "label_mapping": {
      "0": 0,
      "1": 1,
      "2": 2,
      "3": 3,
      "4": 4,
      "5": 5,
      "6": 6,
      "7": 7,
      "8": 8,
      "-1": 9
    },
    "original_values": [
      0,
      1,
      2,
      3,
      4,
      5,
      6,
      7,
      8,
      -1
    ],
    "labels": [
      0,
      1,
      2,
      3,
      4,
      5,
      6,
      7,
      8,
      9
    ],
    "class_names": [
      "Bare Ground",
      "Built Area",
      "Cropland",
      "Flooded Vegetation",
      "Grassland",
      "Mangroves",
      "Shrubland",
      "Trees",
      "Water",
      "No Data"
    ],
    "palette": [
      "#B4B4B4",
      "#FA0000",
      "#F096FF",
      "#7A87C6",
      "#FFFF4C",
      "#00CF75",
      "#FFBB22",
      "#006400",
      "#0064C8",
      "#000000"
    ],
    "vis_params": {
      "min": 0,
      "max": 10
    }
  },
  "_canonical_palette": {
    "trees": "#006400",
    "shrubland": "#FFBB22",
    "grassland": "#FFFF4C",
    "cropland": "#F096FF",
    "flooded_vegetation": "#7A87C6",
    "herbaceous_wetland": "#0096A0",
    "mangroves": "#00CF75",
    "moss_lichen": "#FAE6A0",
    "sparse_vegetation": "#B4B4B4",
    "built_up": "#FA0000",
    "bare": "#B4B4B4",
    "snow_ice": "#F0F0F0",
    "water": "#0064C8",
    "ocean": "#003E80",
    "clouds": "#FFFFFF",
    "no_data": "#000000"
  }
}